mknotebooks/__init__.py
mknotebooks/_version.py
mknotebooks/extra_args_execute_preprocessor.py
mknotebooks/pandas_output_formatter.py
mknotebooks/plugin.py
mknotebooks/templates/ansi-colours.css
mknotebooks/templates/custom_markdown.tpl
mknotebooks/templates/jupyter-cells.css
mknotebooks/templates/pandas-dataframe.css
mknotebooks_with_links-0.7.1.post0.dev809.dist-info/LICENSE
mknotebooks_with_links-0.7.1.post0.dev809.dist-info/METADATA
mknotebooks_with_links-0.7.1.post0.dev809.dist-info/WHEEL
mknotebooks_with_links-0.7.1.post0.dev809.dist-info/entry_points.txt
mknotebooks_with_links-0.7.1.post0.dev809.dist-info/top_level.txt
mknotebooks_with_links-0.7.1.post0.dev809.dist-info/RECORD
